padalam/01/sengo.py
padalam/02/sengo.py
padalam/03/sengo.py
padalam/04/sengo.py
padalam/05/sengo.py
padalam/06/sengo.py
padalam/07/sengo.py
padalam/08/sengo.py
padalam/09/sengo.py
padalam/10/sengo.py
sengo/sengo.py
sengo/vaayil.py
sengo-0.0.1.dist-info/LICENSE
sengo-0.0.1.dist-info/METADATA
sengo-0.0.1.dist-info/WHEEL
sengo-0.0.1.dist-info/top_level.txt
sengo-0.0.1.dist-info/RECORD
