Metadata-Version: 2.1
Name: sengo
Version: 0.0.1
Summary: Sengo regular expression engine from scratch for Tamil Text
Author-email: vanangamudi <selva.developer@gmail.com>
License: GNU GENERAL PUBLIC LICENSE
Project-URL: Homepage, https://github.com/vanangamudi/sengo
Project-URL: Bug Tracker, https://github.com/vanangamudi/sengo/issues
Classifier: Programming Language :: Python :: 3
Classifier: Operating System :: OS Independent
Requires-Python: >=3.5
License-File: LICENSE
